LICENSE
MANIFEST.in
README.rst
buildout.cfg
setup.py
version.txt
bob/__init__.py
bob.db.casiasurf.egg-info/PKG-INFO
bob.db.casiasurf.egg-info/SOURCES.txt
bob.db.casiasurf.egg-info/dependency_links.txt
bob.db.casiasurf.egg-info/entry_points.txt
bob.db.casiasurf.egg-info/not-zip-safe
bob.db.casiasurf.egg-info/requires.txt
bob.db.casiasurf.egg-info/top_level.txt
bob/db/__init__.py
bob/db/casiasurf/__init__.py
bob/db/casiasurf/create.py
bob/db/casiasurf/driver.py
bob/db/casiasurf/models.py
bob/db/casiasurf/query.py
bob/db/casiasurf/test.py
doc/conf.py
doc/guide.rst
doc/index.rst
doc/py_api.rst