Metadata-Version: 1.1
Name: bob.db.casiasurf
Version: 1.0.3
Summary: Bob Database interface for the CASIA-SURF database
Home-page: http://gitlab.idiap.ch/heusch/bob.db.casiasurf
Author: Guillaume Heusch
Author-email: guillaume.heusch@idiap.ch
License: BSD
Keywords: bob,database,casia-surf
Platform: UNKNOWN
Classifier: Framework :: Bob
Classifier: Natural Language :: English
Classifier: Programming Language :: Python
Classifier: Programming Language :: Python :: 3
Classifier: Development Status :: 4 - Beta
Classifier: Intended Audience :: Developers
Classifier: License :: OSI Approved :: BSD License
Classifier: Topic :: Software Development :: Libraries :: Python Modules
